forgeai.py
src/__init__.py
src/ai_client.py
src/ai_tools.py
src/command_processor.py
src/commands.py
src/config.py
src/debug_config.py
src/input_handler.py
src/keyboard_handler.py
src/modes.py
src/output_monitor.py
src/prompt_templates.py
src/snake_game.py
src/thinking_animation.py
src/todo_manager.py
src/todo_renderer.py
src/ui.py
forge_ai_code-1.2.7.dist-info/METADATA
forge_ai_code-1.2.7.dist-info/WHEEL
forge_ai_code-1.2.7.dist-info/entry_points.txt
forge_ai_code-1.2.7.dist-info/top_level.txt
forge_ai_code-1.2.7.dist-info/RECORD
