Metadata-Version: 2.4
Name: forge-ai-code
Version: 1.2.7
Summary: 智能AI编程助手 - 支持多种AI模型的自适应提示词系统，新增删除文件工具和工具调用限制
Home-page: https://github.com/forge-ai/forge-ai-code
Author: Forge AI Team
Author-email: Forge AI Team <support@forgeai.dev>
Maintainer-email: Forge AI Team <support@forgeai.dev>
License: MIT
Project-URL: Homepage, https://forge-ai-code.dev/
Project-URL: Documentation, https://forge-ai-code.readthedocs.io/
Project-URL: Repository, https://github.com/forge-ai/forge-ai-code
Project-URL: Bug Reports, https://github.com/forge-ai/forge-ai-code/issues
Project-URL: Changelog, https://github.com/forge-ai/forge-ai-code/blob/main/VERSION.md
Keywords: ai,artificial-intelligence,coding,programming,assistant,automation,development,cli,tool,prompt-engineering,multi-model,adaptive
Classifier: Development Status :: 4 - Beta
Classifier: Intended Audience :: Developers
Classifier: Topic :: Software Development :: Code Generators
Classifier: Topic :: Software Development :: Libraries :: Python Modules
Classifier: License :: OSI Approved :: MIT License
Classifier: Programming Language :: Python :: 3
Classifier: Programming Language :: Python :: 3.8
Classifier: Programming Language :: Python :: 3.9
Classifier: Programming Language :: Python :: 3.10
Classifier: Programming Language :: Python :: 3.11
Classifier: Programming Language :: Python :: 3.12
Classifier: Operating System :: OS Independent
Classifier: Environment :: Console
Requires-Python: >=3.8
Requires-Dist: colorama>=0.4.4
Requires-Dist: requests>=2.25.1
Provides-Extra: dev
Requires-Dist: pytest>=6.0; extra == "dev"
Requires-Dist: black>=21.0; extra == "dev"
Requires-Dist: flake8>=3.8; extra == "dev"
Requires-Dist: mypy>=0.910; extra == "dev"
Provides-Extra: test
Requires-Dist: pytest>=6.0; extra == "test"
Requires-Dist: pytest-cov>=2.12; extra == "test"
Dynamic: author
Dynamic: home-page
Dynamic: requires-python
